AUTHORS.rst
CONTRIBUTING.rst
HISTORY.rst
LICENSE
MANIFEST.in
README.rst
setup.cfg
setup.py
install_qt_binding.egg-info/PKG-INFO
install_qt_binding.egg-info/SOURCES.txt
install_qt_binding.egg-info/dependency_links.txt
install_qt_binding.egg-info/not-zip-safe
install_qt_binding.egg-info/top_level.txt
installqtbinding/__init__.py
tests/__init__.py
tests/test_installqtbinding.py