Metadata-Version: 1.1
Name: install-qt-binding
Version: 0.0.8
Summary: Automatic install a qt binding (pyside/pyside2/pyqt/pyqt5) that could install in the runtime environment
Home-page: https://github.com/starofrainnight/install-qt-binding
Author: Hong-She Liang
Author-email: starofrainnight@gmail.com
License: Apache Software License
Keywords: installqtbinding,install-qt-binding
Platform: UNKNOWN
Classifier: Development Status :: 2 - Pre-Alpha
Classifier: Intended Audience :: Developers
Classifier: License :: OSI Approved :: Apache Software License
Classifier: Natural Language :: English
Classifier: Programming Language :: Python :: 2.7
Classifier: Programming Language :: Python :: 3
Classifier: Programming Language :: Python :: 3.4
Classifier: Programming Language :: Python :: 3.5
Classifier: Programming Language :: Python :: 3.6
